<?xml version="1.0" ?>

<Problem>

  <Included>
    <File name="./SingleFracCompression_smoke.xml"/>
  </Included>

<!-- SPHINX_SOLVER -->
  <Solvers
    gravityVector="{0.0, 0.0, 0.0}">
    <SolidMechanicsLagrangeContact
      name="lagrangiancontact"
      timeIntegrationOption="QuasiStatic"
      stabilizationName="TPFAstabilization"
      logLevel="1"
      discretization="FE1"
      targetRegions="{ Region, Fracture }">
      <NonlinearSolverParameters
        newtonTol="1.0e-8"
        logLevel="2"
        newtonMaxIter="10"
        maxNumConfigurationAttempts="10"
        lineSearchAction="Require"
        lineSearchMaxCuts="2"
        maxTimeStepCuts="2"/>
      <LinearSolverParameters
        solverType="direct"
        directParallel="0"
        logLevel="0"/>
    </SolidMechanicsLagrangeContact>
  </Solvers>
<!-- SPHINX_SOLVER_END -->

  <NumericalMethods>
    <FiniteVolume>
      <TwoPointFluxApproximation
        name="TPFAstabilization"/>
    </FiniteVolume>
  </NumericalMethods>

  <Events
    maxTime="1.0">
    <SoloEvent
      name="preFracture"
      target="/Solvers/SurfaceGen"/>

    <PeriodicEvent
      name="solverApplications"
      beginTime="0.0"
      forceDt="1.0"
      target="/Solvers/lagrangiancontact"/>

    <PeriodicEvent
      name="outputs"
      timeFrequency="1"
      targetExactTimestep="0"
      target="/Outputs/vtkOutput"/>
    
    <PeriodicEvent
      name="restarts"
      timeFrequency="1.0"
      targetExactTimestep="0"
      target="/Outputs/restartOutput"/>  
 
    <PeriodicEvent
      name="timeHistoryCollection"
      timeFrequency="1"
      targetExactTimestep="1"
      target="/Tasks/tractionCollection" />

    <PeriodicEvent
      name="timeHistoryOutput"
      timeFrequency="1"
      targetExactTimestep="0"
      target="/Outputs/timeHistoryOutput"/>

    <PeriodicEvent
      name="timeHistoryCollection1"
      timeFrequency="1"
      targetExactTimestep="1"
      target="/Tasks/displacementJumpCollection" />

    <PeriodicEvent
      name="timeHistoryOutput1"
      timeFrequency="1"
      targetExactTimestep="0"
      target="/Outputs/timeHistoryOutput1"/>    
  </Events> 
</Problem>
